LICENSE
MANIFEST.in
README.md
setup.py
django_ticketing.egg-info/PKG-INFO
django_ticketing.egg-info/SOURCES.txt
django_ticketing.egg-info/dependency_links.txt
django_ticketing.egg-info/not-zip-safe
django_ticketing.egg-info/top_level.txt
ticketing/__init__.py
ticketing/conf.py
ticketing/exceptions.py
ticketing/fields.py
ticketing/managers.py
ticketing/models.py
ticketing/views.py