Metadata-Version: 1.1
Name: django-ticketing
Version: 0.7.3
Summary: Generate tickets efficiently in a database in Django
Home-page: http://github.com/streeter/django-ticketing
Author: Chris Streeter
Author-email: pypi@chrisstreeter.com
License: Copyright (c) 2013 Chris Streeter
